cynic/__init__.py
cynic/server.py
cynic/utils.py
cynic/handlers/__init__.py
cynic/handlers/base.py
cynic/handlers/httphtml.py
cynic/handlers/httpjson.py
cynic/handlers/httpnone.py
cynic/handlers/httpslow.py
cynic/handlers/log.py
cynic/handlers/noresp.py
cynic/handlers/reset.py
cynic/handlers/rnd.py
cynic3-3.0.dist-info/DESCRIPTION.rst
cynic3-3.0.dist-info/METADATA
cynic3-3.0.dist-info/RECORD
cynic3-3.0.dist-info/WHEEL
cynic3-3.0.dist-info/entry_points.txt
cynic3-3.0.dist-info/metadata.json
cynic3-3.0.dist-info/top_level.txt
