Metadata-Version: 2.0
Name: cynic3
Version: 3.0
Summary: Test harness to make your system under test cynical
Home-page: https://github.com/m-messiah/cynic3
Author: Maxim Muzafarov
Author-email: m.muzafarov@gmail.com
License: MIT
Platform: UNKNOWN
Classifier: Intended Audience :: Developers
Classifier: License :: OSI Approved :: MIT License
Classifier: Programming Language :: Python
Classifier: Topic :: Software Development :: Testing
Classifier: Operating System :: Unix
Requires-Dist: logsna
